LICENSE
MANIFEST.in
README.md
changelog.md
setup.cfg
setup.py
ConfigSpace/__init__.py
ConfigSpace/__version__.py
ConfigSpace/c_util.pyx
ConfigSpace/conditions.pxd
ConfigSpace/conditions.pyx
ConfigSpace/configuration_space.pyx
ConfigSpace/exceptions.py
ConfigSpace/forbidden.pxd
ConfigSpace/forbidden.pyx
ConfigSpace/hyperparameters.pxd
ConfigSpace/hyperparameters.pyx
ConfigSpace/util.pyx
ConfigSpace/nx/__init__.py
ConfigSpace/nx/exception.py
ConfigSpace/nx/release.py
ConfigSpace/nx/algorithms/__init__.py
ConfigSpace/nx/algorithms/cycles.py
ConfigSpace/nx/algorithms/dag.py
ConfigSpace/nx/algorithms/components/__init__.py
ConfigSpace/nx/algorithms/components/strongly_connected.py
ConfigSpace/nx/classes/__init__.py
ConfigSpace/nx/classes/digraph.py
ConfigSpace/nx/classes/graph.py
ConfigSpace/read_and_write/__init__.py
ConfigSpace/read_and_write/irace.py
ConfigSpace/read_and_write/json.py
ConfigSpace/read_and_write/pcs.py
ConfigSpace/read_and_write/pcs_new.py
ConfigSpaceX.egg-info/PKG-INFO
ConfigSpaceX.egg-info/SOURCES.txt
ConfigSpaceX.egg-info/dependency_links.txt
ConfigSpaceX.egg-info/requires.txt
ConfigSpaceX.egg-info/top_level.txt
test/test_conditions.py
test/test_configuration_space.py
test/test_forbidden.py
test/test_hyperparameters.py
test/test_util.py